hypdelta/__init__.py
hypdelta/calculus_utils.py
hypdelta/cartesian.py
hypdelta/condensed.py
hypdelta/cudaprep.py
hypdelta/delta.py
hypdelta/fast.py
hypdelta/naive.py
hypdelta-0.1.47.dist-info/LICENSE
hypdelta-0.1.47.dist-info/METADATA
hypdelta-0.1.47.dist-info/WHEEL
hypdelta-0.1.47.dist-info/RECORD
